scrapeo/__init__.py
scrapeo/core.py
scrapeo/exceptions.py
scrapeo/helpers.py
scrapeo/main.py
scrapeo/utils/__init__.py
scrapeo/utils/web_scraper.py
scrapeo-0.1.1.dist-info/DESCRIPTION.rst
scrapeo-0.1.1.dist-info/METADATA
scrapeo-0.1.1.dist-info/RECORD
scrapeo-0.1.1.dist-info/WHEEL
scrapeo-0.1.1.dist-info/entry_points.txt
scrapeo-0.1.1.dist-info/metadata.json
scrapeo-0.1.1.dist-info/top_level.txt
tests/__init__.py
tests/test_dom_navigator.py
tests/test_element_analyzer.py
tests/test_helpers.py
tests/test_scrapeo.py
