Metadata-Version: 2.0
Name: scrapeo
Version: 0.1.1
Summary: A command-line SEO web scraping / analysis tool
Home-page: http://www.scrapeo.org
Author: Paul Morris
Author-email: wheresmyjetpack03@gmail.com
License: GPL
Keywords: python tools utils internet www
Platform: UNKNOWN
Classifier: Development Status :: 5 - Production/Stable
Classifier: Natural Language :: English
Classifier: Operating System :: MacOS :: MacOS X
Classifier: Operating System :: POSIX :: Linux
Classifier: Intended Audience :: Developers
Classifier: Programming Language :: Python
Classifier: Programming Language :: Python :: 2
Classifier: Programming Language :: Python :: 3
Classifier: License :: OSI Approved :: GNU Library or Lesser General Public License (LGPL)
Classifier: License :: OSI Approved :: GNU Affero General Public License v3
Classifier: Topic :: Internet
Classifier: Topic :: Internet :: WWW/HTTP
Requires-Dist: beautifulsoup4
Requires-Dist: html5lib
Requires-Dist: requests
Requires-Dist: setuptools
